collective.wfautodoc-1.2.0-py3.8-nspkg.pth
collective/wfautodoc/__init__.py
collective/wfautodoc/configure.zcml
collective/wfautodoc/generator.py
collective/wfautodoc/views.py
collective.wfautodoc-1.2.0.dist-info/LICENSE.rst
collective.wfautodoc-1.2.0.dist-info/METADATA
collective.wfautodoc-1.2.0.dist-info/WHEEL
collective.wfautodoc-1.2.0.dist-info/entry_points.txt
collective.wfautodoc-1.2.0.dist-info/namespace_packages.txt
collective.wfautodoc-1.2.0.dist-info/top_level.txt
collective.wfautodoc-1.2.0.dist-info/RECORD
