Metadata-Version: 2.1
Name: collective.wfautodoc
Version: 1.2.0
Summary: Generates a Graphviz file (or directly creates an SVG) from a Zope/CMF DCWorkflow defintion.
Home-page: https://github.com/collective/collective.wfautodoc
Author: Jens Klein
Author-email: jk@kleinundpartner.at
License: BSD
Keywords: zope plone workflow docu graphviz dot svg
Platform: UNKNOWN
Classifier: Environment :: Web Environment
Classifier: Framework :: Plone
Classifier: Framework :: Plone :: Addon
Classifier: Framework :: Plone :: 5.2
Classifier: Framework :: Zope
Classifier: Framework :: Zope :: 4
Classifier: Framework :: Zope :: 5
Classifier: License :: OSI Approved :: GNU General Public License (GPL)
Classifier: Operating System :: OS Independent
Classifier: Programming Language :: Python
Classifier: Programming Language :: Python :: 3.7
Classifier: Programming Language :: Python :: 3.8
Classifier: Programming Language :: Python :: 3.9
Classifier: Topic :: Internet :: WWW/HTTP :: Dynamic Content
Classifier: Development Status :: 5 - Production/Stable
Requires-Dist: setuptools
Requires-Dist: pygraphviz
Requires-Dist: Products.CMFCore
Requires-Dist: Products.DCWorkflow
